{
    "classes": [
        "Inscriptions",
        "ObjectTypes",
        "ObjectMaterials",
        "ObjectPreservationStates",
        "ObjectExecutionTechniques",
        "ObjectDecorationTags",
        "TextFunctions",
        "VerseTimingTypes",
        "Languages",
        "CurrentLocations",
        "Places",
        "Provinces",
        "ModernStates",
        "People",
        "PeopleGenders",
        "PeopleAges",
        "PeopleAgeExpressions",
        "PeopleAgePrecision",
        "PeopleOrigins",
        "PeopleLegalStatus",
        "PeopleRanks",
        "PeopleProfessions",
        "PeopleRoles",
        "DatingCriteria",
        "VerseTypes",
        "Religions",
        "WorkStatus",
        "TextLayoutTags",
        "InscriptionEdited"
    ],
    "enums": [
        "ObjectTypes",
        "ObjectMaterials",
        "ObjectPreservationStates",
        "ObjectExecutionTechniques",
        "TextFunctions",
        "Languages",
        "CurrentLocations",
        "Places",
        "Provinces",
        "PeopleGenders",
        "PeopleAges",
        "PeopleAgeExpressions",
        "PeopleAgePrecision",
        "PeopleOrigins",
        "PeopleLegalStatus",
        "PeopleRanks",
        "PeopleProfessions",
        "PeopleRoles",
        "DatingCriteria",
        "Religions",
        "WorkStatus",
        "TextLayoutTags"
    ],
    "relations": {
        "Translations": {
            "on": "Inscriptions",
            "per": "inscription_id"
        },
        "Publications": {
            "on": "Inscriptions",
            "per": "inscription_id"
        },
        "People": {
            "on": "Inscriptions",
            "per": "inscription_id"
        }
    },
    "summary": {
        "_enums": {
            "create_op": "New Item",
            "update_op": "Rename",
            "delete_op": false,
            "table": [
                {
                    "name": "#",
                    "value": "loop#index"
                },
                {
                    "name": "Title",
                    "value": "obj#title"
                },
                {
                    "name": "LOD",
                    "value": "obj#enum_lod"
                }
            ]
        },
        "Inscriptions": {
            "create_op": "Add Inscription",
            "update_op": false,
            "delete_op": false,
            "show_only_own_op": "Show mine",
            "show_all_op": "Show all (only mine shown)",
            "show_only_own_column": "last_updated_by",
            "table": [
                {
                    "name": "#",
                    "value": "obj#long_id()",
                    "linkto": "show"
                },
                {
                    "name": "Name",
                    "value": "obj#title"
                },
                {
                    "name": "Trismegistos-ID",
                    "value": "obj#trismegistos_nr"
                },
                {
                    "name": "Created",
                    "value": "obj#update_str()"
                },
                {
                    "name": "Work Status",
                    "value": "obj#work_status_str()"
                }
            ]
        },
        "Translations": {
            "create_op": "Add Translation",
            "update_op": "Update",
            "delete_op": "Remove",
            "table": [
                {
                    "name": "#",
                    "value": "loop#index"
                },
                {
                    "name": "Language",
                    "value": "obj#language_title()"
                },
                {
                    "name": "Translation",
                    "value": "obj#link_to_published_translation"
                },
                {
                    "name": "Author",
                    "value": "obj#translation_author"
                }
            ]
        },
        "People": {
            "create_op": "Add Person",
            "update_op": "Update",
            "delete_op": "Remove",
            "table": [
                {
                    "name": "#",
                    "value": "loop#index"
                },
                {
                    "name": "Name",
                    "value": "obj#name"
                },
                {
                    "name": "Romans 1by1 Link",
                    "value": "obj#r1b1_link"
                },
                {
                    "name": "Trismegistos Link",
                    "value": "obj#trismegistos_link"
                }
            ]
        },
        "Publications": {
            "create_op": "Add Publication",
            "update_op": "Update",
            "delete_op": "Remove",
            "table": [
                {
                    "name": "#",
                    "value": "loop#index"
                },
                {
                    "name": "Reference",
                    "value": "obj#reference_comment"
                },
                {
                    "name": "Zotero ID",
                    "value": "obj#zotero_item_id"
                }
            ]
        },
        "Places": {
            "create_op": "New Item",
            "update_op": "Update",
            "delete_op": false,
            "table": [
                {
                    "name": "#",
                    "value": "loop#index"
                },
                {
                    "name": "Title",
                    "value": "obj#title"
                },
                {
                    "name": "Ancient Name",
                    "value": "obj#ancient_name"
                },
                {
                    "name": "Modern Name",
                    "value": "obj#modern_name"
                }
            ]
        },
        "VerseTypes": {
            "create_op": "New Item",
            "update_op": "Update",
            "delete_op": false,
            "table": [
                {
                    "name": "#",
                    "value": "loop#index"
                },
                {
                    "name": "Title",
                    "value": "obj#title"
                },
                {
                    "name": "Parent Type",
                    "value": "obj#parent_verse_name()"
                },
                {
                    "name": "LOD",
                    "value": "obj#enum_lod"
                }
            ]
        },
        "ObjectDecorationTags": {
            "create_op": "New Item",
            "update_op": "Update",
            "delete_op": false,
            "table": [
                {
                    "name": "#",
                    "value": "loop#index"
                },
                {
                    "name": "Title",
                    "value": "obj#title"
                },
                {
                    "name": "Parent Tag",
                    "value": "obj#parent_object_decoration_tag_name()"
                },
                {
                    "name": "LOD",
                    "value": "obj#enum_lod"
                }
            ]
        },
        "VerseTimingTypes": {
            "create_op": "New Item",
            "update_op": "Update",
            "delete_op": false,
            "table": [
                {
                    "name": "#",
                    "value": "loop#index"
                },
                {
                    "name": "Title",
                    "value": "obj#title"
                }
            ]
        },
        "ModernStates": {
            "create_op": "New Item",
            "update_op": "Update",
            "delete_op": false,
            "table": [
                {
                    "name": "#",
                    "value": "loop#index"
                },
                {
                    "name": "Title",
                    "value": "obj#title"
                },
                {
                    "name": "GeoNames-ID",
                    "value": "obj#enum_lod"
                }
            ]
        }
    },
    "display": {
        "_enums": {
            "create_action": "Create",
            "update_action": "Rename",
            "cancel_action": "Cancel",
            "update_op": "Edit This Item",
            "delete_op": false,
            "title": "obj#title",
            "slides": [
                {
                    "title": null,
                    "parts": [
                        {
                            "title": null,
                            "edit_prefix": "Choose a name, under which this item will be shown across this database:",
                            "component": "table",
                            "columns": [
                                {
                                    "column": "title",
                                    "label": "Name",
                                    "type": "input"
                                },
                                {
                                    "column": "enum_lod",
                                    "label": "LOD",
                                    "type": "input"
                                }
                            ]
                        }
                    ]
                }
            ]
        },
        "Inscriptions": {
            "create_action": "Create",
            "update_action": "Update",
            "cancel_action": "Cancel",
            "update_op": "Edit This Inscription",
            "delete_op": false,
            "title": "obj#title",
            "add_create_user_to": "last_updated_by",
            "add_revisions_to_table": "InscriptionEdited:inscription",
            "perform_epidoc_update": true,
            "slides": [
                {
                    "title": "Identification",
                    "parts": [
                        {
                            "title": null,
                            "component": "table",
                            "columns": [
                                {
                                    "column": "obj#long_id()",
                                    "label": "Reference as:",
                                    "type": "call"
                                },
                                {
                                    "column": "title",
                                    "label": "Title",
                                    "type": "input"
                                },
                                {
                                    "column": "trismegistos_nr",
                                    "label": "Trismegistos-No.",
                                    "type": "input"
                                }
                            ]
                        }
                    ]
                },
                {
                    "title": "Object",
                    "parts": [
                        {
                            "title": "Provenance and Location",
                            "component": "table",
                            "edit_prefix": "Longitude and Latitude: these are the coordinates where this Inscription was found. If unknown/empty use zero for both.",
                            "columns": [
                                {
                                    "column": "place",
                                    "label": "Find Place",
                                    "type": "reference",
                                    "refersto": "Places",
                                    "reference_grouping": {
                                        "attribute": "modern_state_id",
                                        "representation": "obj#modern_state_name()"
                                    }
                                },
                                {
                                    "column": "find_comment",
                                    "label": "Find Context",
                                    "type": "text"
                                },
                                {
                                    "column": "coordinates_lat",
                                    "label": "Latitude",
                                    "type": "input"
                                },
                                {
                                    "column": "coordinates_long",
                                    "label": "Longitude",
                                    "type": "input"
                                },
                                {
                                    "column": "current_location",
                                    "label": "Current Location",
                                    "type": "reference",
                                    "refersto": "CurrentLocations"
                                },
                                {
                                    "column": "current_location_inventory",
                                    "label": "Inventory number",
                                    "type": "input"
                                },
                                {
                                    "column": "current_location_details",
                                    "label": "Current Location Details",
                                    "type": "text"
                                }
                            ]
                        },
                        {
                            "title": "Object Details",
                            "component": "table",
                            "columns": [
                                {
                                    "column": "object_type",
                                    "label": "Object Type",
                                    "type": "reference",
                                    "refersto": "ObjectTypes"
                                },
                                {
                                    "column": "object_material",
                                    "label": "Material",
                                    "type": "reference",
                                    "refersto": "ObjectMaterials"
                                },
                                {
                                    "column": "object_preservation_state",
                                    "label": "State of Preservation",
                                    "type": "reference",
                                    "refersto": "ObjectPreservationStates"
                                },
                                {
                                    "column": [
                                        "object_dim_width",
                                        "object_dim_height",
                                        "object_dim_depth"
                                    ],
                                    "label": "Dimensions",
                                    "type": "dimension"
                                },
                                {
                                    "column": "letter_size_min",
                                    "label": "Letter Size in cm (min)",
                                    "type": "numeric_input",
                                    "step": 0.1
                                },
                                {
                                    "column": "letter_size_max",
                                    "label": "Letter Size in cm (max)",
                                    "type": "numeric_input",
                                    "step": 0.1
                                },
                                {
                                    "column": "object_execution_technique",
                                    "label": "Execution Technique",
                                    "type": "reference",
                                    "refersto": "ObjectExecutionTechniques"
                                },
                                {
                                    "column": "religion",
                                    "label": "Religion",
                                    "type": "reference",
                                    "refersto": "Religions"
                                }
                            ]
                        },
                        {
                            "title": "Decoration and Layout",
                            "component": "table",
                            "columns": [
                                {
                                    "column": "object_decoration_comment",
                                    "label": "Decoration and Iconography",
                                    "type": "text"
                                },
                                {
                                    "column": "decoration_tags",
                                    "label": "Decoration Tags",
                                    "type": "reference_list",
                                    "refersto": "ObjectDecorationTags",
                                    "reference_grouping": {
                                        "attribute": "parent_object_decoration_tag_id",
                                        "id_if_equal": true,
                                        "representation": "obj#parent_object_decoration_tag_name()"
                                    }
                                },
                                {
                                    "column": "object_text_layout_comment",
                                    "label": "Text Layout",
                                    "type": "text"
                                },
                                {
                                    "column": "object_text_layout_tags",
                                    "label": "Text Layout Tags",
                                    "type": "reference_list",
                                    "refersto": "TextLayoutTags"
                                }
                            ]
                        }
                    ]
                },
                {
                    "title": "Text",
                    "parts": [
                        {
                            "title": null,
                            "component": "table",
                            "columns": [
                                {
                                    "column": "text_function",
                                    "label": "Function",
                                    "type": "reference",
                                    "refersto": "TextFunctions"
                                },
                                {
                                    "column": "languages",
                                    "label": "Language(s)",
                                    "type": "reference_list",
                                    "refersto": "Languages"
                                },
                                {
                                    "column": "layout_conditioned_by_language",
                                    "label": "Layout Conditioned by Language?",
                                    "type": "boolean_input",
                                    "post_process": "bool"
                                },
                                {
                                    "column": "verse_types",
                                    "label": "Verse Type(s)",
                                    "type": "reference_list",
                                    "refersto": "VerseTypes",
                                    "reference_grouping": {
                                        "attribute": "parent_verse_type_id",
                                        "id_if_equal": true,
                                        "representation": "obj#parent_verse_name()"
                                    }
                                },
                                {
                                    "column": "verse_timing_type",
                                    "label": "Verse Timing Type",
                                    "type": "reference",
                                    "refersto": "VerseTimingTypes"
                                }
                            ]
                        }
                    ]
                },
                {
                    "title": "Inscription & Translations",
                    "parts": [
                        {
                            "title": null,
                            "component": "text_view",
                            "columns": {
                                "epidoc": "text_epidoc_form"
                            }
                        },
                        {
                            "title": null,
                            "component": "standalone",
                            "single": {
                                "column": "text_apparatus_criticus_comment",
                                "label": "Apparatus Criticus",
                                "type": "text",
                                "post_process": "text:nl2br"
                            }
                        },
                        {
                            "title": "Main Translation",
                            "component": "table",
                            "columns": [
                                {
                                    "column": "main_translation",
                                    "label": "Translation",
                                    "type": "text"
                                },
                                {
                                    "column": "translation_author",
                                    "label": "Author",
                                    "type": "input"
                                }
                            ]
                        },
                        {
                            "title": "Other Translations",
                            "component": "standalone",
                            "single": {
                                "column": "translations",
                                "label": "Other Translations",
                                "type": "reference_func",
                                "render": "display",
                                "refersto": "Translations"
                            }
                        }
                    ]
                },
                {
                    "title": "Prosopographical Information",
                    "parts": [
                        {
                            "title": null,
                            "component": "standalone",
                            "single": {
                                "column": "people",
                                "label": "",
                                "type": "reference_func",
                                "render": "display",
                                "refersto": "People"
                            }
                        }
                    ]
                },
                {
                    "title": "Further Information",
                    "parts": [
                        {
                            "title": "Comment",
                            "component": "standalone",
                            "single": {
                                "column": "general_comment",
                                "label": "Comment",
                                "type": "text"
                            }
                        },
                        {
                            "title": "Squeeze",
                            "component": "table",
                            "columns": [
                                {
                                    "column": "have_squeeze",
                                    "label": "Have Squeeze?",
                                    "type": "boolean_input",
                                    "post_process": "bool"
                                }
                            ]
                        },
                        {
                            "title": "Dating Information",
                            "component": "table",
                            "edit_prefix": "Begin the number with a '-' for dates B.C.",
                            "columns": [
                                {
                                    "column": "date_begin",
                                    "label": "Date (From)",
                                    "type": "input",
                                    "post_process": "date"
                                },
                                {
                                    "column": "date_end",
                                    "label": "Date (To)",
                                    "type": "input",
                                    "post_process": "date"
                                },
                                {
                                    "column": "dating_criteria",
                                    "label": "Date (Criteria)",
                                    "type": "reference_list",
                                    "refersto": "DatingCriteria"
                                }
                            ]
                        },
                        {
                            "title": "Bibliography",
                            "component": "standalone",
                            "single": {
                                "column": "publications",
                                "label": "Comment",
                                "type": "reference_func",
                                "render": "display",
                                "refersto": "Publications",
                                "order": "order_number",
                                "ext_linkage": "zotero"
                            }
                        },
                        {
                            "title": "Editing History",
                            "component": "table",
                            "columns": [
                                {
                                    "column": "obj#update_str()",
                                    "label": "Created",
                                    "type": "call"
                                },
                                {
                                    "column": "work_status",
                                    "label": "Work Status",
                                    "type": "reference",
                                    "refersto": "WorkStatus"
                                }
                            ]
                        },
                        {
                            "component": "revisions"
                        }
                    ]
                }
            ]
        },
        "Translations": {
            "create_action": "Create",
            "update_action": "Update",
            "cancel_action": "Cancel",
            "update_op": "Edit This Translation",
            "delete_op": false,
            "title": "obj#title",
            "slides": [
                {
                    "title": null,
                    "parts": [
                        {
                            "title": "Translation",
                            "component": "table",
                            "columns": [
                                {
                                    "column": "language",
                                    "label": "Language",
                                    "type": "reference",
                                    "refersto": "Languages"
                                },
                                {
                                    "column": "link_to_published_translation",
                                    "label": "Translation",
                                    "type": "text"
                                },
                                {
                                    "column": "translation_author",
                                    "label": "Author",
                                    "type": "input"
                                }
                            ]
                        }
                    ]
                }
            ]
        },
        "Publications": {
            "create_action": "Create",
            "update_action": "Update",
            "cancel_action": "Cancel",
            "update_op": "Edit This Publication",
            "delete_op": false,
            "title": "obj#title",
            "slides": [
                {
                    "title": null,
                    "parts": [
                        {
                            "title": null,
                            "component": "standalone",
                            "ext_hint": "zotero",
                            "single": {
                                    "column": "zotero_item_id",
                                    "label": "Zotero Item ID",
                                    "type": "input"
                            }
                        },
                        {
                            "title": null,
                            "component": "standalone",
                            "single": {
                                    "column": "reference_comment",
                                    "label": "Reference description (use | for link-text division)",
                                    "type": "text"
                            }
                        },
                        {
                            "title": null,
                            "component": "standalone",
                            "single": {
                                    "column": "order_number",
                                    "label": "Order Number",
                                    "type": "input"
                            }
                        }
                    ]
                }
            ]
        },
        "Places": {
            "create_action": "Create",
            "update_action": "Update",
            "cancel_action": "Cancel",
            "update_op": "Edit This Item",
            "delete_op": false,
            "title": "obj#title",
            "slides": [
                {
                    "title": null,
                    "parts": [
                        {
                            "title": "General",
                            "component": "table",
                            "columns": [
                                {
                                    "column": "title",
                                    "label": "Title",
                                    "type": "input"
                                }
                            ]
                        },
                        {
                            "title": "Ancient Classification",
                            "component": "table",
                            "columns": [
                                {
                                    "column": "ancient_name",
                                    "label": "Ancient Name",
                                    "type": "input"
                                },
                                {
                                    "column": "province",
                                    "label": "Province",
                                    "type": "reference",
                                    "refersto": "Provinces"
                                }
                            ]
                        },
                        {
                            "title": "Modern Classification",
                            "component": "table",
                            "columns": [
                                {
                                    "column": "modern_name",
                                    "label": "Modern Name",
                                    "type": "input"
                                },
                                {
                                    "column": "modern_state",
                                    "label": "Modern State",
                                    "type": "reference",
                                    "refersto": "ModernStates"
                                },
                                {
                                    "column": "pleiades_id",
                                    "label": "Pleiades-ID",
                                    "type": "input"
                                },
                                {
                                    "column": "geonames_id",
                                    "label": "GeoNames-ID",
                                    "type": "input"
                                }
                            ]
                        },
                        {
                            "title": "Location",
                            "component": "table",
                            "edit_prefix": "Longitude and Latitude coordinates for this Place. If unknown/empty use zero for both.",
                            "ext_hint": "pleiades",
                            "columns": [
                                {
                                    "column": "coordinates_lat",
                                    "label": "Latitude",
                                    "type": "input"
                                },
                                {
                                    "column": "coordinates_long",
                                    "label": "Longitude",
                                    "type": "input"
                                }
                            ]
                        }
                    ]
                }
            ]
        },
        "VerseTypes": {
            "create_action": "Create",
            "update_action": "Update",
            "cancel_action": "Cancel",
            "update_op": "Edit This Item",
            "delete_op": false,
            "title": "obj#title",
            "slides": [
                {
                    "title": null,
                    "parts": [
                        {
                            "title": null,
                            "edit_prefix": "Choose a name, under which this item will be shown across this database:",
                            "component": "table",
                            "columns": [
                                {
                                    "column": "title",
                                    "label": "Name",
                                    "type": "input"
                                },
                                {
                                    "column": "parent_verse_type",
                                    "label": "Parent Verse Type (may be blank)",
                                    "type": "reference",
                                    "refersto": "VerseTypes"
                                },
                                {
                                    "column": "enum_lod",
                                    "label": "LOD",
                                    "type": "input"
                                }
                            ]
                        }
                    ]
                }
            ]
        },
        "ObjectDecorationTags": {
            "create_action": "Create",
            "update_action": "Update",
            "cancel_action": "Cancel",
            "update_op": "Edit This Item",
            "delete_op": false,
            "title": "obj#title",
            "slides": [
                {
                    "title": null,
                    "parts": [
                        {
                            "title": null,
                            "edit_prefix": "Choose a name, under which this item will be shown across this database:",
                            "component": "table",
                            "columns": [
                                {
                                    "column": "title",
                                    "label": "Name",
                                    "type": "input"
                                },
                                {
                                    "column": "parent_object_decoration_tag",
                                    "label": "Parent Decoration Tag (may be blank)",
                                    "type": "reference",
                                    "refersto": "ObjectDecorationTags"
                                },
                                {
                                    "column": "enum_lod",
                                    "label": "LOD",
                                    "type": "input"
                                }
                            ]
                        }
                    ]
                }
            ]
        },
        "VerseTimingTypes": {
            "create_action": "Create",
            "update_action": "Update",
            "cancel_action": "Cancel",
            "update_op": "Edit This Item",
            "delete_op": false,
            "title": "obj#title",
            "slides": [
                {
                    "title": null,
                    "parts": [
                        {
                            "title": null,
                            "edit_prefix": "Choose a name, under which this item will be shown across this database:",
                            "component": "table",
                            "columns": [
                                {
                                    "column": "title",
                                    "label": "Name",
                                    "type": "input"
                                }
                            ]
                        }
                    ]
                }
            ]
        },
        "ModernStates": {
            "create_action": "Create",
            "update_action": "Rename",
            "cancel_action": "Cancel",
            "update_op": "Edit This Item",
            "delete_op": false,
            "title": "obj#title",
            "slides": [
                {
                    "title": null,
                    "parts": [
                        {
                            "title": null,
                            "edit_prefix": "Choose a name, under which this item will be shown across this database:",
                            "component": "table",
                            "columns": [
                                {
                                    "column": "title",
                                    "label": "Name",
                                    "type": "input"
                                },
                                {
                                    "column": "enum_lod",
                                    "label": "GeoNames-ID",
                                    "type": "input"
                                }
                            ]
                        }
                    ]
                }
            ]
        },
        "People": {
            "create_action": "Create",
            "update_action": "Update",
            "cancel_action": "Cancel",
            "update_op": "Edit This Person",
            "delete_op": false,
            "title": "obj#name",
            "slides": [
                {
                    "title": null,
                    "parts": [
                        {
                            "title": null,
                            "component": "table",
                            "columns": [
                                {
                                    "column": "name",
                                    "label": "Name",
                                    "type": "input"
                                },
                                {
                                    "column": "gender",
                                    "label": "Gender",
                                    "type": "reference",
                                    "refersto": "PeopleGenders"
                                },
                                {
                                    "column": "age",
                                    "label": "Age Range",
                                    "type": "reference",
                                    "refersto": "PeopleAges"
                                },
                                {
                                    "column": "age_expression",
                                    "label": "Age Expression",
                                    "type": "reference",
                                    "refersto": "PeopleAgeExpressions"
                                },
                                {
                                    "column": "age_precision",
                                    "label": "Age Precision",
                                    "type": "reference",
                                    "refersto": "PeopleAgePrecision"
                                },
                                {
                                    "column": "origin",
                                    "label": "Origin",
                                    "type": "reference",
                                    "refersto": "PeopleOrigins"
                                },
                                {
                                    "column": "legal_status",
                                    "label": "Legal Status",
                                    "type": "reference",
                                    "refersto": "PeopleLegalStatus"
                                },
                                {
                                    "column": "rank",
                                    "label": "Rank",
                                    "type": "reference",
                                    "refersto": "PeopleRanks"
                                },
                                {
                                    "column": "profession",
                                    "label": "Profession",
                                    "type": "reference",
                                    "refersto": "PeopleProfessions"
                                },
                                {
                                    "column": "r1b1_link",
                                    "label": "Romans 1by1 Link",
                                    "type": "input"
                                },
                                {
                                    "column": "trismegistos_link",
                                    "label": "Trismegistos Link",
                                    "type": "input"
                                },
                                {
                                    "column": "role",
                                    "label": "Role",
                                    "type": "reference",
                                    "refersto": "PeopleRoles"
                                }
                            ]
                        }
                    ]
                }
            ]
        }
    }
}